<?xml version="1.0" encoding="utf-8" ?><dwsync><file name="Hcu.eot" server="https://www0.homecu.net:8443/preview/_packages/silver/" local="3649264133" remote="3649354725" Dst="-1" /><file name="Hcu.svg" server="https://www0.homecu.net:8443/preview/_packages/silver/" local="3649264133" remote="3649354725" Dst="-1" /><file name="Hcu.ttf" server="https://www0.homecu.net:8443/preview/_packages/silver/" local="3649264133" remote="3649354726" Dst="-1" /><file name="Hcu.woff" server="https://www0.homecu.net:8443/preview/_packages/silver/" local="3649264133" remote="3649354727" Dst="-1" /><file name="Hcu.eot" server="https://www0.homecu.net:8443/preview/_packages/silver/jorgen/" local="3649264133" remote="3649432685" Dst="-1" /><file name="Hcu.svg" server="https://www0.homecu.net:8443/preview/_packages/silver/jorgen/" local="3649264133" remote="3649432688" Dst="-1" /><file name="Hcu.ttf" server="https://www0.homecu.net:8443/preview/_packages/silver/jorgen/" local="3649264133" remote="3649432689" Dst="-1" /><file name="Hcu.woff" server="https://www0.homecu.net:8443/preview/_packages/silver/jorgen/" local="3649264133" remote="3649432690" Dst="-1" /></dwsync>